proj1_make/TOP/RTL/baud_gen.v
`timescale 1ns / 1ps 

module baud_gen #(
    parameter   DIV = 8'd216
)(
        i_clk       ,
        i_nRst      ,
        o_tick_16x  

);

input           i_clk       ;
input           i_nRst      ;
output          o_tick_16x  ;

reg     [7:0]   r_count     ;

always@( posedge i_clk or negedge i_nRst ) begin
    if (!i_nRst) begin
        r_count <= 8'd0         ;
    end
    else if (r_count == DIV) begin
        r_count <= 8'd0         ;
    end
    else begin
        r_count <= r_count + 1  ;
    end
end

assign o_tick_16x = ( r_count == DIV )  ;

endmodule

proj1_make/TOP/SIM/TESTBENCH/tb_baud_gen.v
`timescale 1ns / 1ps

module tb_baud_gen ();

parameter CLK_PERIOD = 30;

reg     i_clk           ;
reg     i_nRst          ;
wire    w_tick_16x      ;

baud_gen dut (
        .i_clk       (i_clk     ),
        .i_nRst      (i_nRst    ),
        .o_tick_16x  (w_tick_16x)
);

initial i_clk = 1'b0;
always #(CLK_PERIOD/2) i_clk = ~i_clk;

initial begin
    i_nRst = 1'b0       ;
    #(CLK_PERIOD * 4 )  ;
    i_nRst = 1'b1       ;
end

initial begin
    #(CLK_PERIOD * 655) ;
    $stop               ;
end

initial begin
$dumpfile("./DUMP/baud_gen.vcd");
$dumpvars(0, tb_baud_gen);
end

endmodule

proj1_make/TOP/SIM/FUNCTION/DUMP/baud_gen.vcd
$date
    Sep 23, 2026  14:18:22
$end
$version
    TOOL:	xmsim(64)	22.03-s012
$end
$timescale
    1 ps
$end

$scope module tb_baud_gen $end
$var parameter 32 !    CLK_PERIOD $end
$var reg       1 "    i_clk $end
$var reg       1 #    i_nRst $end
$var wire      1 $    w_tick_16x  $end

$scope module dut $end
$var parameter  8 %    DIV $end
$var wire      1 &    i_clk  $end
$var wire      1 '    i_nRst  $end
$var wire      1 $    o_tick_16x  $end
$var reg       8 (    r_count [7:0] $end
$upscope $end

$upscope $end

$enddefinitions $end
$dumpvars
b11011000 %
b11110 !
0"
0#
0$
0&
0'
b0 (
$end
#15000
1"
1&
#30000
0"
0&
#45000
1"
1&
#60000
0"
0&
#75000
1"
1&
#90000
0"
0&
#105000
1"
1&
#120000
1#
0"
0&
1'
#135000
1"
1&
b1 (
#150000
0"
0&
#165000
1"
1&
b10 (
#180000
0"
0&
#195000
1"
1&
b11 (
#210000
0"
0&
#225000
1"
1&
b100 (
#240000
0"
0&
#255000
1"
1&
b101 (
#270000
0"
0&
#285000
1"
1&
b110 (
#300000
0"
0&
#315000
1"
1&
b111 (
#330000
0"
0&
#345000
1"
1&
b1000 (
#360000
0"
0&
#375000
1"
1&
b1001 (
#390000
0"
0&
#405000
1"
1&
b1010 (
#420000
0"
0&
#435000
1"
1&
b1011 (
#450000
0"
0&
#465000
1"
1&
b1100 (
#480000
0"
0&
#495000
1"
1&
b1101 (
#510000
0"
0&
#525000
1"
1&
b1110 (
#540000
0"
0&
#555000
1"
1&
b1111 (
#570000
0"
0&
#585000
1"
1&
b10000 (
#600000
0"
0&
#615000
1"
1&
b10001 (
#630000
0"
0&
#645000
1"
1&
b10010 (
#660000
0"
0&
#675000
1"
1&
b10011 (
#690000
0"
0&
#705000
1"
1&
b10100 (
#720000
0"
0&
#735000
1"
1&
b10101 (
#750000
0"
0&
#765000
1"
1&
b10110 (
#780000
0"
0&
#795000
1"
1&
b10111 (
#810000
0"
0&
#825000
1"
1&
b11000 (
#840000
0"
0&
#855000
1"
1&
b11001 (
#870000
0"
0&
#885000
1"
1&
b11010 (
#900000
0"
0&
#915000
1"
1&
b11011 (
#930000
0"
0&
#945000
1"
1&
b11100 (
#960000
0"
0&
#975000
1"
1&
b11101 (
#990000
0"
0&
#1005000
1"
1&
b11110 (
#1020000
0"
0&
#1035000
1"
1&
b11111 (
#1050000
0"
0&
#1065000
1"
1&
b100000 (
#1080000
0"
0&
#1095000
1"
1&
b100001 (
#1110000
0"
0&
#1125000
1"
1&
b100010 (
#1140000
0"
0&
#1155000
1"
1&
b100011 (
#1170000
0"
0&
#1185000
1"
1&
b100100 (
#1200000
0"
0&
#1215000
1"
1&
b100101 (
#1230000
0"
0&
#1245000
1"
1&
b100110 (
#1260000
0"
0&
#1275000
1"
1&
b100111 (
#1290000
0"
0&
#1305000
1"
1&
b101000 (
#1320000
0"
0&
#1335000
1"
1&
b101001 (
#1350000
0"
0&
#1365000
1"
1&
b101010 (
#1380000
0"
0&
#1395000
1"
1&
b101011 (
#1410000
0"
0&
#1425000
1"
1&
b101100 (
#1440000
0"
0&
#1455000
1"
1&
b101101 (
#1470000
0"
0&
#1485000
1"
1&
b101110 (
#1500000
0"
0&
#1515000
1"
1&
b101111 (
#1530000
0"
0&
#1545000
1"
1&
b110000 (
#1560000
0"
0&
#1575000
1"
1&
b110001 (
#1590000
0"
0&
#1605000
1"
1&
b110010 (
#1620000
0"
0&
#1635000
1"
1&
b110011 (
#1650000
0"
0&
#1665000
1"
1&
b110100 (
#1680000
0"
0&
#1695000
1"
1&
b110101 (
#1710000
0"
0&
#1725000
1"
1&
b110110 (
#1740000
0"
0&
#1755000
1"
1&
b110111 (
#1770000
0"
0&
#1785000
1"
1&
b111000 (
#1800000
0"
0&
#1815000
1"
1&
b111001 (
#1830000
0"
0&
#1845000
1"
1&
b111010 (
#1860000
0"
0&
#1875000
1"
1&
b111011 (
#1890000
0"
0&
#1905000
1"
1&
b111100 (
#1920000
0"
0&
#1935000
1"
1&
b111101 (
#1950000
0"
0&
#1965000
1"
1&
b111110 (
#1980000
0"
0&
#1995000
1"
1&
b111111 (
#2010000
0"
0&
#2025000
1"
1&
b1000000 (
#2040000
0"
0&
#2055000
1"
1&
b1000001 (
#2070000
0"
0&
#2085000
1"
1&
b1000010 (
#2100000
0"
0&
#2115000
1"
1&
b1000011 (
#2130000
0"
0&
#2145000
1"
1&
b1000100 (
#2160000
0"
0&
#2175000
1"
1&
b1000101 (
#2190000
0"
0&
#2205000
1"
1&
b1000110 (
#2220000
0"
0&
#2235000
1"
1&
b1000111 (
#2250000
0"
0&
#2265000
1"
1&
b1001000 (
#2280000
0"
0&
#2295000
1"
1&
b1001001 (
#2310000
0"
0&
#2325000
1"
1&
b1001010 (
#2340000
0"
0&
#2355000
1"
1&
b1001011 (
#2370000
0"
0&
#2385000
1"
1&
b1001100 (
#2400000
0"
0&
#2415000
1"
1&
b1001101 (
#2430000
0"
0&
#2445000
1"
1&
b1001110 (
#2460000
0"
0&
#2475000
1"
1&
b1001111 (
#2490000
0"
0&
#2505000
1"
1&
b1010000 (
#2520000
0"
0&
#2535000
1"
1&
b1010001 (
#2550000
0"
0&
#2565000
1"
1&
b1010010 (
#2580000
0"
0&
#2595000
1"
1&
b1010011 (
#2610000
0"
0&
#2625000
1"
1&
b1010100 (
#2640000
0"
0&
#2655000
1"
1&
b1010101 (
#2670000
0"
0&
#2685000
1"
1&
b1010110 (
#2700000
0"
0&
#2715000
1"
1&
b1010111 (
#2730000
0"
0&
#2745000
1"
1&
b1011000 (
#2760000
0"
0&
#2775000
1"
1&
b1011001 (
#2790000
0"
0&
#2805000
1"
1&
b1011010 (
#2820000
0"
0&
#2835000
1"
1&
b1011011 (
#2850000
0"
0&
#2865000
1"
1&
b1011100 (
#2880000
0"
0&
#2895000
1"
1&
b1011101 (
#2910000
0"
0&
#2925000
1"
1&
b1011110 (
#2940000
0"
0&
#2955000
1"
1&
b1011111 (
#2970000
0"
0&
#2985000
1"
1&
b1100000 (
#3000000
0"
0&
#3015000
1"
1&
b1100001 (
#3030000
0"
0&
#3045000
1"
1&
b1100010 (
#3060000
0"
0&
#3075000
1"
1&
b1100011 (
#3090000
0"
0&
#3105000
1"
1&
b1100100 (
#3120000
0"
0&
#3135000
1"
1&
b1100101 (
#3150000
0"
0&
#3165000
1"
1&
b1100110 (
#3180000
0"
0&
#3195000
1"
1&
b1100111 (
#3210000
0"
0&
#3225000
1"
1&
b1101000 (
#3240000
0"
0&
#3255000
1"
1&
b1101001 (
#3270000
0"
0&
#3285000
1"
1&
b1101010 (
#3300000
0"
0&
#3315000
1"
1&
b1101011 (
#3330000
0"
0&
#3345000
1"
1&
b1101100 (
#3360000
0"
0&
#3375000
1"
1&
b1101101 (
#3390000
0"
0&
#3405000
1"
1&
b1101110 (
#3420000
0"
0&
#3435000
1"
1&
b1101111 (
#3450000
0"
0&
#3465000
1"
1&
b1110000 (
#3480000
0"
0&
#3495000
1"
1&
b1110001 (
#3510000
0"
0&
#3525000
1"
1&
b1110010 (
#3540000
0"
0&
#3555000
1"
1&
b1110011 (
#3570000
0"
0&
#3585000
1"
1&
b1110100 (
#3600000
0"
0&
#3615000
1"
1&
b1110101 (
#3630000
0"
0&
#3645000
1"
1&
b1110110 (
#3660000
0"
0&
#3675000
1"
1&
b1110111 (
#3690000
0"
0&
#3705000
1"
1&
b1111000 (
#3720000
0"
0&
#3735000
1"
1&
b1111001 (
#3750000
0"
0&
#3765000
1"
1&
b1111010 (
#3780000
0"
0&
#3795000
1"
1&
b1111011 (
#3810000
0"
0&
#3825000
1"
1&
b1111100 (
#3840000
0"
0&
#3855000
1"
1&
b1111101 (
#3870000
0"
0&
#3885000
1"
1&
b1111110 (
#3900000
0"
0&
#3915000
1"
1&
b1111111 (
#3930000
0"
0&
#3945000
1"
1&
b10000000 (
#3960000
0"
0&
#3975000
1"
1&
b10000001 (
#3990000
0"
0&
#4005000
1"
1&
b10000010 (
#4020000
0"
0&
#4035000
1"
1&
b10000011 (
#4050000
0"
0&
#4065000
1"
1&
b10000100 (
#4080000
0"
0&
#4095000
1"
1&
b10000101 (
#4110000
0"
0&
#4125000
1"
1&
b10000110 (
#4140000
0"
0&
#4155000
1"
1&
b10000111 (
#4170000
0"
0&
#4185000
1"
1&
b10001000 (
#4200000
0"
0&
#4215000
1"
1&
b10001001 (
#4230000
0"
0&
#4245000
1"
1&
b10001010 (
#4260000
0"
0&
#4275000
1"
1&
b10001011 (
#4290000
0"
0&
#4305000
1"
1&
b10001100 (
#4320000
0"
0&
#4335000
1"
1&
b10001101 (
#4350000
0"
0&
#4365000
1"
1&
b10001110 (
#4380000
0"
0&
#4395000
1"
1&
b10001111 (
#4410000
0"
0&
#4425000
1"
1&
b10010000 (
#4440000
0"
0&
#4455000
1"
1&
b10010001 (
#4470000
0"
0&
#4485000
1"
1&
b10010010 (
#4500000
0"
0&
#4515000
1"
1&
b10010011 (
#4530000
0"
0&
#4545000
1"
1&
b10010100 (
#4560000
0"
0&
#4575000
1"
1&
b10010101 (
#4590000
0"
0&
#4605000
1"
1&
b10010110 (
#4620000
0"
0&
#4635000
1"
1&
b10010111 (
#4650000
0"
0&
#4665000
1"
1&
b10011000 (
#4680000
0"
0&
#4695000
1"
1&
b10011001 (
#4710000
0"
0&
#4725000
1"
1&
b10011010 (
#4740000
0"
0&
#4755000
1"
1&
b10011011 (
#4770000
0"
0&
#4785000
1"
1&
b10011100 (
#4800000
0"
0&
#4815000
1"
1&
b10011101 (
#4830000
0"
0&
#4845000
1"
1&
b10011110 (
#4860000
0"
0&
#4875000
1"
1&
b10011111 (
#4890000
0"
0&
#4905000
1"
1&
b10100000 (
#4920000
0"
0&
#4935000
1"
1&
b10100001 (
#4950000
0"
0&
#4965000
1"
1&
b10100010 (
#4980000
0"
0&
#4995000
1"
1&
b10100011 (
#5010000
0"
0&
#5025000
1"
1&
b10100100 (
#5040000
0"
0&
#5055000
1"
1&
b10100101 (
#5070000
0"
0&
#5085000
1"
1&
b10100110 (
#5100000
0"
0&
#5115000
1"
1&
b10100111 (
#5130000
0"
0&
#5145000
1"
1&
b10101000 (
#5160000
0"
0&
#5175000
1"
1&
b10101001 (
#5190000
0"
0&
#5205000
1"
1&
b10101010 (
#5220000
0"
0&
#5235000
1"
1&
b10101011 (
#5250000
0"
0&
#5265000
1"
1&
b10101100 (
#5280000
0"
0&
#5295000
1"
1&
b10101101 (
#5310000
0"
0&
#5325000
1"
1&
b10101110 (
#5340000
0"
0&
#5355000
1"
1&
b10101111 (
#5370000
0"
0&
#5385000
1"
1&
b10110000 (
#5400000
0"
0&
#5415000
1"
1&
b10110001 (
#5430000
0"
0&
#5445000
1"
1&
b10110010 (
#5460000
0"
0&
#5475000
1"
1&
b10110011 (
#5490000
0"
0&
#5505000
1"
1&
b10110100 (
#5520000
0"
0&
#5535000
1"
1&
b10110101 (
#5550000
0"
0&
#5565000
1"
1&
b10110110 (
#5580000
0"
0&
#5595000
1"
1&
b10110111 (
#5610000
0"
0&
#5625000
1"
1&
b10111000 (
#5640000
0"
0&
#5655000
1"
1&
b10111001 (
#5670000
0"
0&
#5685000
1"
1&
b10111010 (
#5700000
0"
0&
#5715000
1"
1&
b10111011 (
#5730000
0"
0&
#5745000
1"
1&
b10111100 (
#5760000
0"
0&
#5775000
1"
1&
b10111101 (
#5790000
0"
0&
#5805000
1"
1&
b10111110 (
#5820000
0"
0&
#5835000
1"
1&
b10111111 (
#5850000
0"
0&
#5865000
1"
1&
b11000000 (
#5880000
0"
0&
#5895000
1"
1&
b11000001 (
#5910000
0"
0&
#5925000
1"
1&
b11000010 (
#5940000
0"
0&
#5955000
1"
1&
b11000011 (
#5970000
0"
0&
#5985000
1"
1&
b11000100 (
#6000000
0"
0&
#6015000
1"
1&
b11000101 (
#6030000
0"
0&
#6045000
1"
1&
b11000110 (
#6060000
0"
0&
#6075000
1"
1&
b11000111 (
#6090000
0"
0&
#6105000
1"
1&
b11001000 (
#6120000
0"
0&
#6135000
1"
1&
b11001001 (
#6150000
0"
0&
#6165000
1"
1&
b11001010 (
#6180000
0"
0&
#6195000
1"
1&
b11001011 (
#6210000
0"
0&
#6225000
1"
1&
b11001100 (
#6240000
0"
0&
#6255000
1"
1&
b11001101 (
#6270000
0"
0&
#6285000
1"
1&
b11001110 (
#6300000
0"
0&
#6315000
1"
1&
b11001111 (
#6330000
0"
0&
#6345000
1"
1&
b11010000 (
#6360000
0"
0&
#6375000
1"
1&
b11010001 (
#6390000
0"
0&
#6405000
1"
1&
b11010010 (
#6420000
0"
0&
#6435000
1"
1&
b11010011 (
#6450000
0"
0&
#6465000
1"
1&
b11010100 (
#6480000
0"
0&
#6495000
1"
1&
b11010101 (
#6510000
0"
0&
#6525000
1"
1&
b11010110 (
#6540000
0"
0&
#6555000
1"
1&
b11010111 (
#6570000
0"
0&
#6585000
1"
1&
b11011000 (
1$
#6600000
0"
0&
#6615000
1"
1&
b0 (
0$
#6630000
0"
0&
#6645000
1"
1&
b1 (
#6660000
0"
0&
#6675000
1"
1&
b10 (
#6690000
0"
0&
#6705000
1"
1&
b11 (
#6720000
0"
0&
#6735000
1"
1&
b100 (
#6750000
0"
0&
#6765000
1"
1&
b101 (
#6780000
0"
0&
#6795000
1"
1&
b110 (
#6810000
0"
0&
#6825000
1"
1&
b111 (
#6840000
0"
0&
#6855000
1"
1&
b1000 (
#6870000
0"
0&
#6885000
1"
1&
b1001 (
#6900000
0"
0&
#6915000
1"
1&
b1010 (
#6930000
0"
0&
#6945000
1"
1&
b1011 (
#6960000
0"
0&
#6975000
1"
1&
b1100 (
#6990000
0"
0&
#7005000
1"
1&
b1101 (
#7020000
0"
0&
#7035000
1"
1&
b1110 (
#7050000
0"
0&
#7065000
1"
1&
b1111 (
#7080000
0"
0&
#7095000
1"
1&
b10000 (
#7110000
0"
0&
#7125000
1"
1&
b10001 (
#7140000
0"
0&
#7155000
1"
1&
b10010 (
#7170000
0"
0&
#7185000
1"
1&
b10011 (
#7200000
0"
0&
#7215000
1"
1&
b10100 (
#7230000
0"
0&
#7245000
1"
1&
b10101 (
#7260000
0"
0&
#7275000
1"
1&
b10110 (
#7290000
0"
0&
#7305000
1"
1&
b10111 (
#7320000
0"
0&
#7335000
1"
1&
b11000 (
#7350000
0"
0&
#7365000
1"
1&
b11001 (
#7380000
0"
0&
#7395000
1"
1&
b11010 (
#7410000
0"
0&
#7425000
1"
1&
b11011 (
#7440000
0"
0&
#7455000
1"
1&
b11100 (
#7470000
0"
0&
#7485000
1"
1&
b11101 (
#7500000
0"
0&
#7515000
1"
1&
b11110 (
#7530000
0"
0&
#7545000
1"
1&
b11111 (
#7560000
0"
0&
#7575000
1"
1&
b100000 (
#7590000
0"
0&
#7605000
1"
1&
b100001 (
#7620000
0"
0&
#7635000
1"
1&
b100010 (
#7650000
0"
0&
#7665000
1"
1&
b100011 (
#7680000
0"
0&
#7695000
1"
1&
b100100 (
#7710000
0"
0&
#7725000
1"
1&
b100101 (
#7740000
0"
0&
#7755000
1"
1&
b100110 (
#7770000
0"
0&
#7785000
1"
1&
b100111 (
#7800000
0"
0&
#7815000
1"
1&
b101000 (
#7830000
0"
0&
#7845000
1"
1&
b101001 (
#7860000
0"
0&
#7875000
1"
1&
b101010 (
#7890000
0"
0&
#7905000
1"
1&
b101011 (
#7920000
0"
0&
#7935000
1"
1&
b101100 (
#7950000
0"
0&
#7965000
1"
1&
b101101 (
#7980000
0"
0&
#7995000
1"
1&
b101110 (
#8010000
0"
0&
#8025000
1"
1&
b101111 (
#8040000
0"
0&
#8055000
1"
1&
b110000 (
#8070000
0"
0&
#8085000
1"
1&
b110001 (
#8100000
0"
0&
#8115000
1"
1&
b110010 (
#8130000
0"
0&
#8145000
1"
1&
b110011 (
#8160000
0"
0&
#8175000
1"
1&
b110100 (
#8190000
0"
0&
#8205000
1"
1&
b110101 (
#8220000
0"
0&
#8235000
1"
1&
b110110 (
#8250000
0"
0&
#8265000
1"
1&
b110111 (
#8280000
0"
0&
#8295000
1"
1&
b111000 (
#8310000
0"
0&
#8325000
1"
1&
b111001 (
#8340000
0"
0&
#8355000
1"
1&
b111010 (
#8370000
0"
0&
#8385000
1"
1&
b111011 (
#8400000
0"
0&
#8415000
1"
1&
b111100 (
#8430000
0"
0&
#8445000
1"
1&
b111101 (
#8460000
0"
0&
#8475000
1"
1&
b111110 (
#8490000
0"
0&
#8505000
1"
1&
b111111 (
#8520000
0"
0&
#8535000
1"
1&
b1000000 (
#8550000
0"
0&
#8565000
1"
1&
b1000001 (
#8580000
0"
0&
#8595000
1"
1&
b1000010 (
#8610000
0"
0&
#8625000
1"
1&
b1000011 (
#8640000
0"
0&
#8655000
1"
1&
b1000100 (
#8670000
0"
0&
#8685000
1"
1&
b1000101 (
#8700000
0"
0&
#8715000
1"
1&
b1000110 (
#8730000
0"
0&
#8745000
1"
1&
b1000111 (
#8760000
0"
0&
#8775000
1"
1&
b1001000 (
#8790000
0"
0&
#8805000
1"
1&
b1001001 (
#8820000
0"
0&
#8835000
1"
1&
b1001010 (
#8850000
0"
0&
#8865000
1"
1&
b1001011 (
#8880000
0"
0&
#8895000
1"
1&
b1001100 (
#8910000
0"
0&
#8925000
1"
1&
b1001101 (
#8940000
0"
0&
#8955000
1"
1&
b1001110 (
#8970000
0"
0&
#8985000
1"
1&
b1001111 (
#9000000
0"
0&
#9015000
1"
1&
b1010000 (
#9030000
0"
0&
#9045000
1"
1&
b1010001 (
#9060000
0"
0&
#9075000
1"
1&
b1010010 (
#9090000
0"
0&
#9105000
1"
1&
b1010011 (
#9120000
0"
0&
#9135000
1"
1&
b1010100 (
#9150000
0"
0&
#9165000
1"
1&
b1010101 (
#9180000
0"
0&
#9195000
1"
1&
b1010110 (
#9210000
0"
0&
#9225000
1"
1&
b1010111 (
#9240000
0"
0&
#9255000
1"
1&
b1011000 (
#9270000
0"
0&
#9285000
1"
1&
b1011001 (
#9300000
0"
0&
#9315000
1"
1&
b1011010 (
#9330000
0"
0&
#9345000
1"
1&
b1011011 (
#9360000
0"
0&
#9375000
1"
1&
b1011100 (
#9390000
0"
0&
#9405000
1"
1&
b1011101 (
#9420000
0"
0&
#9435000
1"
1&
b1011110 (
#9450000
0"
0&
#9465000
1"
1&
b1011111 (
#9480000
0"
0&
#9495000
1"
1&
b1100000 (
#9510000
0"
0&
#9525000
1"
1&
b1100001 (
#9540000
0"
0&
#9555000
1"
1&
b1100010 (
#9570000
0"
0&
#9585000
1"
1&
b1100011 (
#9600000
0"
0&
#9615000
1"
1&
b1100100 (
#9630000
0"
0&
#9645000
1"
1&
b1100101 (
#9660000
0"
0&
#9675000
1"
1&
b1100110 (
#9690000
0"
0&
#9705000
1"
1&
b1100111 (
#9720000
0"
0&
#9735000
1"
1&
b1101000 (
#9750000
0"
0&
#9765000
1"
1&
b1101001 (
#9780000
0"
0&
#9795000
1"
1&
b1101010 (
#9810000
0"
0&
#9825000
1"
1&
b1101011 (
#9840000
0"
0&
#9855000
1"
1&
b1101100 (
#9870000
0"
0&
#9885000
1"
1&
b1101101 (
#9900000
0"
0&
#9915000
1"
1&
b1101110 (
#9930000
0"
0&
#9945000
1"
1&
b1101111 (
#9960000
0"
0&
#9975000
1"
1&
b1110000 (
#9990000
0"
0&
#10005000
1"
1&
b1110001 (
#10020000
0"
0&
#10035000
1"
1&
b1110010 (
#10050000
0"
0&
#10065000
1"
1&
b1110011 (
#10080000
0"
0&
#10095000
1"
1&
b1110100 (
#10110000
0"
0&
#10125000
1"
1&
b1110101 (
#10140000
0"
0&
#10155000
1"
1&
b1110110 (
#10170000
0"
0&
#10185000
1"
1&
b1110111 (
#10200000
0"
0&
#10215000
1"
1&
b1111000 (
#10230000
0"
0&
#10245000
1"
1&
b1111001 (
#10260000
0"
0&
#10275000
1"
1&
b1111010 (
#10290000
0"
0&
#10305000
1"
1&
b1111011 (
#10320000
0"
0&
#10335000
1"
1&
b1111100 (
#10350000
0"
0&
#10365000
1"
1&
b1111101 (
#10380000
0"
0&
#10395000
1"
1&
b1111110 (
#10410000
0"
0&
#10425000
1"
1&
b1111111 (
#10440000
0"
0&
#10455000
1"
1&
b10000000 (
#10470000
0"
0&
#10485000
1"
1&
b10000001 (
#10500000
0"
0&
#10515000
1"
1&
b10000010 (
#10530000
0"
0&
#10545000
1"
1&
b10000011 (
#10560000
0"
0&
#10575000
1"
1&
b10000100 (
#10590000
0"
0&
#10605000
1"
1&
b10000101 (
#10620000
0"
0&
#10635000
1"
1&
b10000110 (
#10650000
0"
0&
#10665000
1"
1&
b10000111 (
#10680000
0"
0&
#10695000
1"
1&
b10001000 (
#10710000
0"
0&
#10725000
1"
1&
b10001001 (
#10740000
0"
0&
#10755000
1"
1&
b10001010 (
#10770000
0"
0&
#10785000
1"
1&
b10001011 (
#10800000
0"
0&
#10815000
1"
1&
b10001100 (
#10830000
0"
0&
#10845000
1"
1&
b10001101 (
#10860000
0"
0&
#10875000
1"
1&
b10001110 (
#10890000
0"
0&
#10905000
1"
1&
b10001111 (
#10920000
0"
0&
#10935000
1"
1&
b10010000 (
#10950000
0"
0&
#10965000
1"
1&
b10010001 (
#10980000
0"
0&
#10995000
1"
1&
b10010010 (
#11010000
0"
0&
#11025000
1"
1&
b10010011 (
#11040000
0"
0&
#11055000
1"
1&
b10010100 (
#11070000
0"
0&
#11085000
1"
1&
b10010101 (
#11100000
0"
0&
#11115000
1"
1&
b10010110 (
#11130000
0"
0&
#11145000
1"
1&
b10010111 (
#11160000
0"
0&
#11175000
1"
1&
b10011000 (
#11190000
0"
0&
#11205000
1"
1&
b10011001 (
#11220000
0"
0&
#11235000
1"
1&
b10011010 (
#11250000
0"
0&
#11265000
1"
1&
b10011011 (
#11280000
0"
0&
#11295000
1"
1&
b10011100 (
#11310000
0"
0&
#11325000
1"
1&
b10011101 (
#11340000
0"
0&
#11355000
1"
1&
b10011110 (
#11370000
0"
0&
#11385000
1"
1&
b10011111 (
#11400000
0"
0&
#11415000
1"
1&
b10100000 (
#11430000
0"
0&
#11445000
1"
1&
b10100001 (
#11460000
0"
0&
#11475000
1"
1&
b10100010 (
#11490000
0"
0&
#11505000
1"
1&
b10100011 (
#11520000
0"
0&
#11535000
1"
1&
b10100100 (
#11550000
0"
0&
#11565000
1"
1&
b10100101 (
#11580000
0"
0&
#11595000
1"
1&
b10100110 (
#11610000
0"
0&
#11625000
1"
1&
b10100111 (
#11640000
0"
0&
#11655000
1"
1&
b10101000 (
#11670000
0"
0&
#11685000
1"
1&
b10101001 (
#11700000
0"
0&
#11715000
1"
1&
b10101010 (
#11730000
0"
0&
#11745000
1"
1&
b10101011 (
#11760000
0"
0&
#11775000
1"
1&
b10101100 (
#11790000
0"
0&
#11805000
1"
1&
b10101101 (
#11820000
0"
0&
#11835000
1"
1&
b10101110 (
#11850000
0"
0&
#11865000
1"
1&
b10101111 (
#11880000
0"
0&
#11895000
1"
1&
b10110000 (
#11910000
0"
0&
#11925000
1"
1&
b10110001 (
#11940000
0"
0&
#11955000
1"
1&
b10110010 (
#11970000
0"
0&
#11985000
1"
1&
b10110011 (
#12000000
0"
0&
#12015000
1"
1&
b10110100 (
#12030000
0"
0&
#12045000
1"
1&
b10110101 (
#12060000
0"
0&
#12075000
1"
1&
b10110110 (
#12090000
0"
0&
#12105000
1"
1&
b10110111 (
#12120000
0"
0&
#12135000
1"
1&
b10111000 (
#12150000
0"
0&
#12165000
1"
1&
b10111001 (
#12180000
0"
0&
#12195000
1"
1&
b10111010 (
#12210000
0"
0&
#12225000
1"
1&
b10111011 (
#12240000
0"
0&
#12255000
1"
1&
b10111100 (
#12270000
0"
0&
#12285000
1"
1&
b10111101 (
#12300000
0"
0&
#12315000
1"
1&
b10111110 (
#12330000
0"
0&
#12345000
1"
1&
b10111111 (
#12360000
0"
0&
#12375000
1"
1&
b11000000 (
#12390000
0"
0&
#12405000
1"
1&
b11000001 (
#12420000
0"
0&
#12435000
1"
1&
b11000010 (
#12450000
0"
0&
#12465000
1"
1&
b11000011 (
#12480000
0"
0&
#12495000
1"
1&
b11000100 (
#12510000
0"
0&
#12525000
1"
1&
b11000101 (
#12540000
0"
0&
#12555000
1"
1&
b11000110 (
#12570000
0"
0&
#12585000
1"
1&
b11000111 (
#12600000
0"
0&
#12615000
1"
1&
b11001000 (
#12630000
0"
0&
#12645000
1"
1&
b11001001 (
#12660000
0"
0&
#12675000
1"
1&
b11001010 (
#12690000
0"
0&
#12705000
1"
1&
b11001011 (
#12720000
0"
0&
#12735000
1"
1&
b11001100 (
#12750000
0"
0&
#12765000
1"
1&
b11001101 (
#12780000
0"
0&
#12795000
1"
1&
b11001110 (
#12810000
0"
0&
#12825000
1"
1&
b11001111 (
#12840000
0"
0&
#12855000
1"
1&
b11010000 (
#12870000
0"
0&
#12885000
1"
1&
b11010001 (
#12900000
0"
0&
#12915000
1"
1&
b11010010 (
#12930000
0"
0&
#12945000
1"
1&
b11010011 (
#12960000
0"
0&
#12975000
1"
1&
b11010100 (
#12990000
0"
0&
#13005000
1"
1&
b11010101 (
#13020000
0"
0&
#13035000
1"
1&
b11010110 (
#13050000
0"
0&
#13065000
1"
1&
b11010111 (
#13080000
0"
0&
#13095000
1"
1&
b11011000 (
1$
#13110000
0"
0&
#13125000
1"
1&
b0 (
0$
#13140000
0"
0&
#13155000
1"
1&
b1 (
#13170000
0"
0&
#13185000
1"
1&
b10 (
#13200000
0"
0&
#13215000
1"
1&
b11 (
#13230000
0"
0&
#13245000
1"
1&
b100 (
#13260000
0"
0&
#13275000
1"
1&
b101 (
#13290000
0"
0&
#13305000
1"
1&
b110 (
#13320000
0"
0&
#13335000
1"
1&
b111 (
#13350000
0"
0&
#13365000
1"
1&
b1000 (
#13380000
0"
0&
#13395000
1"
1&
b1001 (
#13410000
0"
0&
#13425000
1"
1&
b1010 (
#13440000
0"
0&
#13455000
1"
1&
b1011 (
#13470000
0"
0&
#13485000
1"
1&
b1100 (
#13500000
0"
0&
#13515000
1"
1&
b1101 (
#13530000
0"
0&
#13545000
1"
1&
b1110 (
#13560000
0"
0&
#13575000
1"
1&
b1111 (
#13590000
0"
0&
#13605000
1"
1&
b10000 (
#13620000
0"
0&
#13635000
1"
1&
b10001 (
#13650000
0"
0&
#13665000
1"
1&
b10010 (
#13680000
0"
0&
#13695000
1"
1&
b10011 (
#13710000
0"
0&
#13725000
1"
1&
b10100 (
#13740000
0"
0&
#13755000
1"
1&
b10101 (
#13770000
0"
0&
#13785000
1"
1&
b10110 (
#13800000
0"
0&
#13815000
1"
1&
b10111 (
#13830000
0"
0&
#13845000
1"
1&
b11000 (
#13860000
0"
0&
#13875000
1"
1&
b11001 (
#13890000
0"
0&
#13905000
1"
1&
b11010 (
#13920000
0"
0&
#13935000
1"
1&
b11011 (
#13950000
0"
0&
#13965000
1"
1&
b11100 (
#13980000
0"
0&
#13995000
1"
1&
b11101 (
#14010000
0"
0&
#14025000
1"
1&
b11110 (
#14040000
0"
0&
#14055000
1"
1&
b11111 (
#14070000
0"
0&
#14085000
1"
1&
b100000 (
#14100000
0"
0&
#14115000
1"
1&
b100001 (
#14130000
0"
0&
#14145000
1"
1&
b100010 (
#14160000
0"
0&
#14175000
1"
1&
b100011 (
#14190000
0"
0&
#14205000
1"
1&
b100100 (
#14220000
0"
0&
#14235000
1"
1&
b100101 (
#14250000
0"
0&
#14265000
1"
1&
b100110 (
#14280000
0"
0&
#14295000
1"
1&
b100111 (
#14310000
0"
0&
#14325000
1"
1&
b101000 (
#14340000
0"
0&
#14355000
1"
1&
b101001 (
#14370000
0"
0&
#14385000
1"
1&
b101010 (
#14400000
0"
0&
#14415000
1"
1&
b101011 (
#14430000
0"
0&
#14445000
1"
1&
b101100 (
#14460000
0"
0&
#14475000
1"
1&
b101101 (
#14490000
0"
0&
#14505000
1"
1&
b101110 (
#14520000
0"
0&
#14535000
1"
1&
b101111 (
#14550000
0"
0&
#14565000
1"
1&
b110000 (
#14580000
0"
0&
#14595000
1"
1&
b110001 (
#14610000
0"
0&
#14625000
1"
1&
b110010 (
#14640000
0"
0&
#14655000
1"
1&
b110011 (
#14670000
0"
0&
#14685000
1"
1&
b110100 (
#14700000
0"
0&
#14715000
1"
1&
b110101 (
#14730000
0"
0&
#14745000
1"
1&
b110110 (
